Workbook

Sheet Inputs
A1: Kinika pricing model — Inputs
A2: Blue cells with yellow fill are editable assumptions. Everything else is a formula.
A4: Credit economics
A5: Credit retail price ($) | B5: 0.02 | E5: What a founder pays per credit via top-ups ($10 / 500).
A6: COGS multiplier (retail ÷ COGS) | B6: 5 | E6: Markup on AI cost. 4x = 75% gross on credits before Stripe/infra.
A7: Credit COGS ($) | B7: =B5/B6 | E7: Derived. Your real cost when a founder spends 1 credit.
A8: Stripe % fee | B8: 0.029 | E8: Standard card rate.
A9: Stripe fixed fee ($) | B9: 0.3 | E9: Per transaction.
A10: Target gross margin | B10: 0.75 | E10: Used for the 'price needed' row on Tiers.
A12: Token assumptions per LLM call
A13: Context pack tokens (Brand DNA + memory) | B13: 6000 | E13: Sent on every agent step. Cached within a run.
A14: Cache hit rate on context pack | B14: 0.9 | E14: Share of context-pack tokens served from prompt cache.
A15: Step-specific input tokens | B15: 2000 | E15: Task brief, tool results, instructions.
A17: Model rates ($ per 1M tokens)
A18: Tier / model | B18: Input | C18: Output | D18: Cache read | E18: Note
A19: Fast (Haiku 4.5) | B19: 1 | C19: 5 | D19: 0.1 | E19: Anthropic first-party rates.
A20: Fast-open (Llama 3.3 70B, DeepInfra) | B20: 0.1 | C20: 0.32 | D20: 0.1 | E20: No prompt cache; cache rate set = input rate.
A21: Standard (Sonnet 5.5) | B21: 2 | C21: 10 | D21: 0.2 | E21: Anthropic first-party rates.
A22: Reasoning (Opus 5.5) | B22: 4 | C22: 20 | D22: 0.2 | E22: Anthropic first-party rates.
A24: Media generation ($ per asset)
A25: Image generation | B25: 0.05 | E25: Mid-tier image model. Estimate — replace with your provider's rate.
A26: Short video clip | B26: 0.5 | E26: Estimate — highly provider dependent.
A27: Code run extras (build / preview deploy) | B27: 0 | E27: Vercel/Netlify preview builds are usually free at this scale.
A29: Overhead steps (planner, approvals, digest, memory write-back)
A30: Overhead model | B30: Fast (Haiku 4.5) | E30: Type a model name exactly as in the table above. Try 'Fast-open (Llama 3.3 70B, DeepInfra)'.
A31: Output tokens per overhead step | B31: 500
A32: Overhead step COGS ($) | B32: =(B13*B14*INDEX($D$19:$D$22,MATCH(B30,$A$19:$A$22,0))+B13*(1-B14)*INDEX($B$19:$B$22,MATCH(B30,$A$19:$A$22,0))+B15*INDEX($B$19:$B$22,MATCH(B30,$A$19:$A$22,0)))/1000000+B31*INDEX($C$19:$C$22,MATCH(B30,$A$19:$A$22,0))/1000000 | E32: Derived. Multiplied by overhead steps/month on the Tiers sheet.
A34: Team members
A35: Infra per team member ($/month) | B35: 0.4 | E35: Auth, storage, realtime, email per human seat. Team members share the workspace credit pool; no credits included per member.
A36: Overhead steps per team member / month | B36: 25 | E36: Each human seat triggers its own planner/digest/memory steps. Added to the tier's base overhead on Tiers.

Sheet Action Costs
A1: Cost and credit price per action
A2: Blue = assumption per action. COGS and credits are formulas driven by Inputs. These rows become the initial pricing_rules table.
A4: Action | B4: Model (LLM step) | C4: Extra input tokens | D4: Output tokens | E4: LLM calls | F4: Fast helper calls | G4: Images | H4: Videos | I4: LLM COGS ($) | J4: Helper COGS ($) | K4: Media COGS ($) | L4: Total COGS ($) | M4: Credits | N4: Range factor | O4: Credits (max)
A5: Fast step (classify / summarize) | B5: Fast (Haiku 4.5) | C5: 0 | D5: 500 | E5: 1 | F5: 0 | G5: 0 | H5: 0 | I5: =E5*((Inputs!$B$13*Inputs!$B$14*INDEX(Inputs!$D$19:$D$22,MATCH(B5,Inputs!$A$19:$A$22,0))+Inputs!$B$13*(1-Inputs!$B$14)*INDEX(Inputs!$B$19:$B$22,MATCH(B5,Inputs!$A$19:$A$22,0))+(Inputs!$B$15+C5)*INDEX(Inputs!$B$19:$B$22,MATCH(B5,Inputs!$A$19:$A$22,0)))/1000000+D5*INDEX(Inputs!$C$19:$C$22,MATCH(B5,Inputs!$A$19:$A$22,0))/1000000) | J5: =F5*$I$5 | K5: =G5*Inputs!$B$25+H5*Inputs!$B$26+IF(B5="Reasoning (Opus 5.5)",Inputs!$B$27,0) | L5: =I5+J5+K5 | M5: =ROUNDUP(L5/Inputs!$B$7,0) | N5: 1 | O5: =ROUNDUP(L5*N5/Inputs!$B$7,0)
A6: Caption / short copy | B6: Standard (Sonnet 5.5) | C6: 0 | D6: 1500 | E6: 1 | F6: 0 | G6: 0 | H6: 0 | I6: =E6*((Inputs!$B$13*Inputs!$B$14*INDEX(Inputs!$D$19:$D$22,MATCH(B6,Inputs!$A$19:$A$22,0))+Inputs!$B$13*(1-Inputs!$B$14)*INDEX(Inputs!$B$19:$B$22,MATCH(B6,Inputs!$A$19:$A$22,0))+(Inputs!$B$15+C6)*INDEX(Inputs!$B$19:$B$22,MATCH(B6,Inputs!$A$19:$A$22,0)))/1000000+D6*INDEX(Inputs!$C$19:$C$22,MATCH(B6,Inputs!$A$19:$A$22,0))/1000000) | J6: =F6*$I$5 | K6: =G6*Inputs!$B$25+H6*Inputs!$B$26+IF(B6="Reasoning (Opus 5.5)",Inputs!$B$27,0) | L6: =I6+J6+K6 | M6: =ROUNDUP(L6/Inputs!$B$7,0) | N6: 1 | O6: =ROUNDUP(L6*N6/Inputs!$B$7,0)
A7: Product SEO refresh (per product) | B7: Standard (Sonnet 5.5) | C7: 0 | D7: 500 | E7: 1 | F7: 1 | G7: 0 | H7: 0 | I7: =E7*((Inputs!$B$13*Inputs!$B$14*INDEX(Inputs!$D$19:$D$22,MATCH(B7,Inputs!$A$19:$A$22,0))+Inputs!$B$13*(1-Inputs!$B$14)*INDEX(Inputs!$B$19:$B$22,MATCH(B7,Inputs!$A$19:$A$22,0))+(Inputs!$B$15+C7)*INDEX(Inputs!$B$19:$B$22,MATCH(B7,Inputs!$A$19:$A$22,0)))/1000000+D7*INDEX(Inputs!$C$19:$C$22,MATCH(B7,Inputs!$A$19:$A$22,0))/1000000) | J7: =F7*$I$5 | K7: =G7*Inputs!$B$25+H7*Inputs!$B$26+IF(B7="Reasoning (Opus 5.5)",Inputs!$B$27,0) | L7: =I7+J7+K7 | M7: =ROUNDUP(L7/Inputs!$B$7,0) | N7: 1 | O7: =ROUNDUP(L7*N7/Inputs!$B$7,0)
A8: Blog post | B8: Standard (Sonnet 5.5) | C8: 2000 | D8: 3000 | E8: 1 | F8: 1 | G8: 0 | H8: 0 | I8: =E8*((Inputs!$B$13*Inputs!$B$14*INDEX(Inputs!$D$19:$D$22,MATCH(B8,Inputs!$A$19:$A$22,0))+Inputs!$B$13*(1-Inputs!$B$14)*INDEX(Inputs!$B$19:$B$22,MATCH(B8,Inputs!$A$19:$A$22,0))+(Inputs!$B$15+C8)*INDEX(Inputs!$B$19:$B$22,MATCH(B8,Inputs!$A$19:$A$22,0)))/1000000+D8*INDEX(Inputs!$C$19:$C$22,MATCH(B8,Inputs!$A$19:$A$22,0))/1000000) | J8: =F8*$I$5 | K8: =G8*Inputs!$B$25+H8*Inputs!$B$26+IF(B8="Reasoning (Opus 5.5)",Inputs!$B$27,0) | L8: =I8+J8+K8 | M8: =ROUNDUP(L8/Inputs!$B$7,0) | N8: 1 | O8: =ROUNDUP(L8*N8/Inputs!$B$7,0)
A9: Designed social post | B9: Standard (Sonnet 5.5) | C9: 0 | D9: 1500 | E9: 1 | F9: 1 | G9: 1 | H9: 0 | I9: =E9*((Inputs!$B$13*Inputs!$B$14*INDEX(Inputs!$D$19:$D$22,MATCH(B9,Inputs!$A$19:$A$22,0))+Inputs!$B$13*(1-Inputs!$B$14)*INDEX(Inputs!$B$19:$B$22,MATCH(B9,Inputs!$A$19:$A$22,0))+(Inputs!$B$15+C9)*INDEX(Inputs!$B$19:$B$22,MATCH(B9,Inputs!$A$19:$A$22,0)))/1000000+D9*INDEX(Inputs!$C$19:$C$22,MATCH(B9,Inputs!$A$19:$A$22,0))/1000000) | J9: =F9*$I$5 | K9: =G9*Inputs!$B$25+H9*Inputs!$B$26+IF(B9="Reasoning (Opus 5.5)",Inputs!$B$27,0) | L9: =I9+J9+K9 | M9: =ROUNDUP(L9/Inputs!$B$7,0) | N9: 1 | O9: =ROUNDUP(L9*N9/Inputs!$B$7,0)
A10: Short video | B10: Standard (Sonnet 5.5) | C10: 0 | D10: 500 | E10: 1 | F10: 0 | G10: 0 | H10: 1 | I10: =E10*((Inputs!$B$13*Inputs!$B$14*INDEX(Inputs!$D$19:$D$22,MATCH(B10,Inputs!$A$19:$A$22,0))+Inputs!$B$13*(1-Inputs!$B$14)*INDEX(Inputs!$B$19:$B$22,MATCH(B10,Inputs!$A$19:$A$22,0))+(Inputs!$B$15+C10)*INDEX(Inputs!$B$19:$B$22,MATCH(B10,Inputs!$A$19:$A$22,0)))/1000000+D10*INDEX(Inputs!$C$19:$C$22,MATCH(B10,Inputs!$A$19:$A$22,0))/1000000) | J10: =F10*$I$5 | K10: =G10*Inputs!$B$25+H10*Inputs!$B$26+IF(B10="Reasoning (Opus 5.5)",Inputs!$B$27,0) | L10: =I10+J10+K10 | M10: =ROUNDUP(L10/Inputs!$B$7,0) | N10: 1 | O10: =ROUNDUP(L10*N10/Inputs!$B$7,0)
A11: Code change (PR) | B11: Reasoning (Opus 5.5) | C11: 52000 | D11: 15000 | E11: 1 | F11: 2 | G11: 0 | H11: 0 | I11: =E11*((Inputs!$B$13*Inputs!$B$14*INDEX(Inputs!$D$19:$D$22,MATCH(B11,Inputs!$A$19:$A$22,0))+Inputs!$B$13*(1-Inputs!$B$14)*INDEX(Inputs!$B$19:$B$22,MATCH(B11,Inputs!$A$19:$A$22,0))+(Inputs!$B$15+C11)*INDEX(Inputs!$B$19:$B$22,MATCH(B11,Inputs!$A$19:$A$22,0)))/1000000+D11*INDEX(Inputs!$C$19:$C$22,MATCH(B11,Inputs!$A$19:$A$22,0))/1000000) | J11: =F11*$I$5 | K11: =G11*Inputs!$B$25+H11*Inputs!$B$26+IF(B11="Reasoning (Opus 5.5)",Inputs!$B$27,0) | L11: =I11+J11+K11 | M11: =ROUNDUP(L11/Inputs!$B$7,0) | N11: 2 | O11: =ROUNDUP(L11*N11/Inputs!$B$7,0)
A13: Code change assumption: ~52k extra input tokens for reading repo files across turns, 15k output. Realistic range $0.40–1.50 per run, hence range factor 2.

Sheet Tiers
A1: Tier economics
A2: Blue = plan design levers. Worst case = founder spends every included credit. Typical = usage % below.
B4: Solo | C4: Startup | D4: Enterprise | E4: Extra agent seat | F4: Extra team member | G4: Top-up $10 | H4: Top-up $20 | I4: Top-up $50
A5: Price ($/month) | B5: 20 | C5: 45 | D5: 139 | E5: 10 | F5: 5 | G5: 10 | H5: 20 | I5: 50
A6: Credits included | B6: 1000 | C6: 2000 | D6: 6000 | E6: 250 | F6: 0 | G6: 500 | H6: 1000 | I6: 2750
A7: Active agents | B7: 2 | C7: 5 | D7: 10 | E7: 1 | F7: 0 | G7: 0 | H7: 0 | I7: 0
A8: Team members included | B8: 1 | C8: 3 | D8: 20 | E8: 0 | F8: 1 | G8: 0 | H8: 0 | I8: 0
A9: Base infra ($/month) | B9: 1.1 | C9: 1.8 | D9: 0 | E9: 0 | F9: 0 | G9: 0 | H9: 0 | I9: 0
A10: Base overhead steps / month | B10: 175 | C10: 225 | D10: 100 | E10: 0 | F10: 0 | G10: 0 | H10: 0 | I10: 0
A11: Typical usage (% of credits) | B11: 0.6 | C11: 0.6 | D11: 0.6 | E11: 1 | F11: 1 | G11: 1 | H11: 1 | I11: 1
A12: Infra share ($/month) | B12: =B9+B8*Inputs!$B$35 | C12: =C9+C8*Inputs!$B$35 | D12: =D9+D8*Inputs!$B$35 | E12: =E9+E8*Inputs!$B$35 | F12: =F9+F8*Inputs!$B$35 | G12: =G9+G8*Inputs!$B$35 | H12: =H9+H8*Inputs!$B$35 | I12: =I9+I8*Inputs!$B$35
A13: Overhead steps / month | B13: =B10+B8*Inputs!$B$36 | C13: =C10+C8*Inputs!$B$36 | D13: =D10+D8*Inputs!$B$36 | E13: =E10+E8*Inputs!$B$36 | F13: =F10+F8*Inputs!$B$36 | G13: =G10+G8*Inputs!$B$36 | H13: =H10+H8*Inputs!$B$36 | I13: =I10+I8*Inputs!$B$36
A14: Costs
A15: Stripe fee ($) | B15: =B5*Inputs!$B$8+Inputs!$B$9 | C15: =C5*Inputs!$B$8+Inputs!$B$9 | D15: =D5*Inputs!$B$8+Inputs!$B$9 | E15: =E5*Inputs!$B$8+Inputs!$B$9 | F15: =F5*Inputs!$B$8+Inputs!$B$9 | G15: =G5*Inputs!$B$8+Inputs!$B$9 | H15: =H5*Inputs!$B$8+Inputs!$B$9 | I15: =I5*Inputs!$B$8+Inputs!$B$9
A16: Overhead COGS ($) | B16: =B13*Inputs!$B$32 | C16: =C13*Inputs!$B$32 | D16: =D13*Inputs!$B$32 | E16: =E13*Inputs!$B$32 | F16: =F13*Inputs!$B$32 | G16: =G13*Inputs!$B$32 | H16: =H13*Inputs!$B$32 | I16: =I13*Inputs!$B$32
A17: Worst-case AI COGS ($) | B17: =B6*Inputs!$B$7 | C17: =C6*Inputs!$B$7 | D17: =D6*Inputs!$B$7 | E17: =E6*Inputs!$B$7 | F17: =F6*Inputs!$B$7 | G17: =G6*Inputs!$B$7 | H17: =H6*Inputs!$B$7 | I17: =I6*Inputs!$B$7
A18: Worst-case total COGS ($) | B18: =B15+B12+B16+B17 | C18: =C15+C12+C16+C17 | D18: =D15+D12+D16+D17 | E18: =E15+E12+E16+E17 | F18: =F15+F12+F16+F17 | G18: =G15+G12+G16+G17 | H18: =H15+H12+H16+H17 | I18: =I15+I12+I16+I17
A19: Worst-case gross margin | B19: =IF(B5=0,0,(B5-B18)/B5) | C19: =IF(C5=0,0,(C5-C18)/C5) | D19: =IF(D5=0,0,(D5-D18)/D5) | E19: =IF(E5=0,0,(E5-E18)/E5) | F19: =IF(F5=0,0,(F5-F18)/F5) | G19: =IF(G5=0,0,(G5-G18)/G5) | H19: =IF(H5=0,0,(H5-H18)/H5) | I19: =IF(I5=0,0,(I5-I18)/I5)
A20: Typical AI COGS ($) | B20: =B6*B11*Inputs!$B$7 | C20: =C6*C11*Inputs!$B$7 | D20: =D6*D11*Inputs!$B$7 | E20: =E6*E11*Inputs!$B$7 | F20: =F6*F11*Inputs!$B$7 | G20: =G6*G11*Inputs!$B$7 | H20: =H6*H11*Inputs!$B$7 | I20: =I6*I11*Inputs!$B$7
A21: Typical total COGS ($) | B21: =B15+B12+B16+B20 | C21: =C15+C12+C16+C20 | D21: =D15+D12+D16+D20 | E21: =E15+E12+E16+E20 | F21: =F15+F12+F16+F20 | G21: =G15+G12+G16+G20 | H21: =H15+H12+H16+H20 | I21: =I15+I12+I16+I20
A22: Typical gross margin | B22: =IF(B5=0,0,(B5-B21)/B5) | C22: =IF(C5=0,0,(C5-C21)/C5) | D22: =IF(D5=0,0,(D5-D21)/D5) | E22: =IF(E5=0,0,(E5-E21)/E5) | F22: =IF(F5=0,0,(F5-F21)/F5) | G22: =IF(G5=0,0,(G5-G21)/G5) | H22: =IF(H5=0,0,(H5-H21)/H5) | I22: =IF(I5=0,0,(I5-I21)/I5)
A23: Price needed for target margin (worst case) | B23: =(Inputs!$B$9+B12+B16+B17)/(1-Inputs!$B$10-Inputs!$B$8) | C23: =(Inputs!$B$9+C12+C16+C17)/(1-Inputs!$B$10-Inputs!$B$8) | D23: =(Inputs!$B$9+D12+D16+D17)/(1-Inputs!$B$10-Inputs!$B$8) | E23: =(Inputs!$B$9+E12+E16+E17)/(1-Inputs!$B$10-Inputs!$B$8) | F23: =(Inputs!$B$9+F12+F16+F17)/(1-Inputs!$B$10-Inputs!$B$8) | G23: =(Inputs!$B$9+G12+G16+G17)/(1-Inputs!$B$10-Inputs!$B$8) | H23: =(Inputs!$B$9+H12+H16+H17)/(1-Inputs!$B$10-Inputs!$B$8) | I23: =(Inputs!$B$9+I12+I16+I17)/(1-Inputs!$B$10-Inputs!$B$8)
A24: Credits affordable at target margin (worst case) | B24: =ROUNDDOWN((B5*(1-Inputs!$B$10-Inputs!$B$8)-Inputs!$B$9-B12-B16)/Inputs!$B$7,-1) | C24: =ROUNDDOWN((C5*(1-Inputs!$B$10-Inputs!$B$8)-Inputs!$B$9-C12-C16)/Inputs!$B$7,-1) | D24: =ROUNDDOWN((D5*(1-Inputs!$B$10-Inputs!$B$8)-Inputs!$B$9-D12-D16)/Inputs!$B$7,-1) | E24: =ROUNDDOWN((E5*(1-Inputs!$B$10-Inputs!$B$8)-Inputs!$B$9-E12-E16)/Inputs!$B$7,-1) | F24: =ROUNDDOWN((F5*(1-Inputs!$B$10-Inputs!$B$8)-Inputs!$B$9-F12-F16)/Inputs!$B$7,-1) | G24: =ROUNDDOWN((G5*(1-Inputs!$B$10-Inputs!$B$8)-Inputs!$B$9-G12-G16)/Inputs!$B$7,-1) | H24: =ROUNDDOWN((H5*(1-Inputs!$B$10-Inputs!$B$8)-Inputs!$B$9-H12-H16)/Inputs!$B$7,-1) | I24: =ROUNDDOWN((I5*(1-Inputs!$B$10-Inputs!$B$8)-Inputs!$B$9-I12-I16)/Inputs!$B$7,-1)
A26: Reading the sheet
A27: Worst-case margin is the floor: a founder who burns the whole pool. Typical margin is what most founders will look like.
A28: 'Price needed' solves price so the worst-case margin equals the Inputs target. 'Credits affordable' holds price and solves the pool instead.
A29: Extra agent seat and top-ups have no infra/overhead allocated; their margin is credits + Stripe only.
A30: Extra team member: $5 covers one human seat's infra. Members share the workspace pool, so more members means faster pool burn and more top-ups — that is where the revenue is.
A31: Not modelled: social aggregator per-profile fees ($1–5/profile/month), support cost, free-trial COGS, churn. Add rows if you adopt an aggregator.

Sheet Typical Month
A1: Typical month by tier — usage mix
A2: Blue = how many of each action a typical founder on that tier runs per month. Credits and COGS pull from Action Costs.
A4: Action | B4: Solo count | C4: Startup count | D4: Enterprise count | E4: Solo credits | F4: Startup credits | G4: Enterprise credits | H4: Credits each | I4: COGS each ($)
A5: Caption / short copy | B5: 20 | C5: 60 | D5: 200 | E5: =B5*$H5 | F5: =C5*$H5 | G5: =D5*$H5 | H5: ='Action Costs'!M6 | I5: ='Action Costs'!L6
A6: Product SEO refresh (per product) | B6: 50 | C6: 150 | D6: 500 | E6: =B6*$H6 | F6: =C6*$H6 | G6: =D6*$H6 | H6: ='Action Costs'!M7 | I6: ='Action Costs'!L7
A7: Blog post | B7: 4 | C7: 8 | D7: 20 | E7: =B7*$H7 | F7: =C7*$H7 | G7: =D7*$H7 | H7: ='Action Costs'!M8 | I7: ='Action Costs'!L8
A8: Designed social post | B8: 12 | C8: 30 | D8: 80 | E8: =B8*$H8 | F8: =C8*$H8 | G8: =D8*$H8 | H8: ='Action Costs'!M9 | I8: ='Action Costs'!L9
A9: Short video | B9: 2 | C9: 4 | D9: 12 | E9: =B9*$H9 | F9: =C9*$H9 | G9: =D9*$H9 | H9: ='Action Costs'!M10 | I9: ='Action Costs'!L10
A10: Code change (PR) | B10: 2 | C10: 4 | D10: 10 | E10: =B10*$H10 | F10: =C10*$H10 | G10: =D10*$H10 | H10: ='Action Costs'!M11 | I10: ='Action Costs'!L11
A11: Total credits used | E11: =SUM(E5:E10) | F11: =SUM(F5:F10) | G11: =SUM(G5:G10)
A12: Credits included (from Tiers) | E12: =Tiers!B6 | F12: =Tiers!C6 | G12: =Tiers!D6
A13: Pool used | E13: =IF(E12=0,0,E11/E12) | F13: =IF(F12=0,0,F11/F12) | G13: =IF(G12=0,0,G11/G12)
A14: Top-up credits needed (if over pool) | E14: =MAX(0,E11-E12) | F14: =MAX(0,F11-F12) | G14: =MAX(0,G11-G12)
A15: Team members on plan (from Tiers) | E15: =Tiers!B8 | F15: =Tiers!C8 | G15: =Tiers!D8
A16: Economics at this mix
A17: Action COGS ($) | E17: =SUMPRODUCT(B5:B10,$I$5:$I$10) | F17: =SUMPRODUCT(C5:C10,$I$5:$I$10) | G17: =SUMPRODUCT(D5:D10,$I$5:$I$10)
A18: Overhead COGS ($) | E18: =Tiers!B16 | F18: =Tiers!C16 | G18: =Tiers!D16
A19: Stripe + infra ($) | E19: =Tiers!B15+Tiers!B12 | F19: =Tiers!C15+Tiers!C12 | G19: =Tiers!D15+Tiers!D12
A20: Top-up revenue if over pool ($) | E20: =E14*Inputs!$B$5 | F20: =F14*Inputs!$B$5 | G20: =G14*Inputs!$B$5
A21: Revenue ($) | E21: =Tiers!B5+E20 | F21: =Tiers!C5+F20 | G21: =Tiers!D5+G20
A22: Total COGS ($) | E22: =E17+E18+E19 | F22: =F17+F18+F19 | G22: =G17+G18+G19
A23: Gross margin at this mix | E23: =IF(E21=0,0,(E21-E22)/E21) | F23: =IF(F21=0,0,(F21-F22)/F21) | G23: =IF(G21=0,0,(G21-G22)/G21)

Sheet Sensitivity
A1: Solo worst-case margin: multiplier × credit pool
A2: Uses Solo price, infra and overhead from Tiers. Rows = COGS multiplier, columns = credits included.
A4: Multiplier ↓ / Pool → | B4: 500 | C4: 750 | D4: 1000 | E4: 1250 | F4: 1500
A5: 3 | B5: =(Tiers!$B$5-(Tiers!$B$5*Inputs!$B$8+Inputs!$B$9+Tiers!$B$12+Tiers!$B$16+B$4*Inputs!$B$5/$A5))/Tiers!$B$5 | C5: =(Tiers!$B$5-(Tiers!$B$5*Inputs!$B$8+Inputs!$B$9+Tiers!$B$12+Tiers!$B$16+C$4*Inputs!$B$5/$A5))/Tiers!$B$5 | D5: =(Tiers!$B$5-(Tiers!$B$5*Inputs!$B$8+Inputs!$B$9+Tiers!$B$12+Tiers!$B$16+D$4*Inputs!$B$5/$A5))/Tiers!$B$5 | E5: =(Tiers!$B$5-(Tiers!$B$5*Inputs!$B$8+Inputs!$B$9+Tiers!$B$12+Tiers!$B$16+E$4*Inputs!$B$5/$A5))/Tiers!$B$5 | F5: =(Tiers!$B$5-(Tiers!$B$5*Inputs!$B$8+Inputs!$B$9+Tiers!$B$12+Tiers!$B$16+F$4*Inputs!$B$5/$A5))/Tiers!$B$5
A6: 4 | B6: =(Tiers!$B$5-(Tiers!$B$5*Inputs!$B$8+Inputs!$B$9+Tiers!$B$12+Tiers!$B$16+B$4*Inputs!$B$5/$A6))/Tiers!$B$5 | C6: =(Tiers!$B$5-(Tiers!$B$5*Inputs!$B$8+Inputs!$B$9+Tiers!$B$12+Tiers!$B$16+C$4*Inputs!$B$5/$A6))/Tiers!$B$5 | D6: =(Tiers!$B$5-(Tiers!$B$5*Inputs!$B$8+Inputs!$B$9+Tiers!$B$12+Tiers!$B$16+D$4*Inputs!$B$5/$A6))/Tiers!$B$5 | E6: =(Tiers!$B$5-(Tiers!$B$5*Inputs!$B$8+Inputs!$B$9+Tiers!$B$12+Tiers!$B$16+E$4*Inputs!$B$5/$A6))/Tiers!$B$5 | F6: =(Tiers!$B$5-(Tiers!$B$5*Inputs!$B$8+Inputs!$B$9+Tiers!$B$12+Tiers!$B$16+F$4*Inputs!$B$5/$A6))/Tiers!$B$5
A7: 5 | B7: =(Tiers!$B$5-(Tiers!$B$5*Inputs!$B$8+Inputs!$B$9+Tiers!$B$12+Tiers!$B$16+B$4*Inputs!$B$5/$A7))/Tiers!$B$5 | C7: =(Tiers!$B$5-(Tiers!$B$5*Inputs!$B$8+Inputs!$B$9+Tiers!$B$12+Tiers!$B$16+C$4*Inputs!$B$5/$A7))/Tiers!$B$5 | D7: =(Tiers!$B$5-(Tiers!$B$5*Inputs!$B$8+Inputs!$B$9+Tiers!$B$12+Tiers!$B$16+D$4*Inputs!$B$5/$A7))/Tiers!$B$5 | E7: =(Tiers!$B$5-(Tiers!$B$5*Inputs!$B$8+Inputs!$B$9+Tiers!$B$12+Tiers!$B$16+E$4*Inputs!$B$5/$A7))/Tiers!$B$5 | F7: =(Tiers!$B$5-(Tiers!$B$5*Inputs!$B$8+Inputs!$B$9+Tiers!$B$12+Tiers!$B$16+F$4*Inputs!$B$5/$A7))/Tiers!$B$5
A8: 6 | B8: =(Tiers!$B$5-(Tiers!$B$5*Inputs!$B$8+Inputs!$B$9+Tiers!$B$12+Tiers!$B$16+B$4*Inputs!$B$5/$A8))/Tiers!$B$5 | C8: =(Tiers!$B$5-(Tiers!$B$5*Inputs!$B$8+Inputs!$B$9+Tiers!$B$12+Tiers!$B$16+C$4*Inputs!$B$5/$A8))/Tiers!$B$5 | D8: =(Tiers!$B$5-(Tiers!$B$5*Inputs!$B$8+Inputs!$B$9+Tiers!$B$12+Tiers!$B$16+D$4*Inputs!$B$5/$A8))/Tiers!$B$5 | E8: =(Tiers!$B$5-(Tiers!$B$5*Inputs!$B$8+Inputs!$B$9+Tiers!$B$12+Tiers!$B$16+E$4*Inputs!$B$5/$A8))/Tiers!$B$5 | F8: =(Tiers!$B$5-(Tiers!$B$5*Inputs!$B$8+Inputs!$B$9+Tiers!$B$12+Tiers!$B$16+F$4*Inputs!$B$5/$A8))/Tiers!$B$5
A9: 7 | B9: =(Tiers!$B$5-(Tiers!$B$5*Inputs!$B$8+Inputs!$B$9+Tiers!$B$12+Tiers!$B$16+B$4*Inputs!$B$5/$A9))/Tiers!$B$5 | C9: =(Tiers!$B$5-(Tiers!$B$5*Inputs!$B$8+Inputs!$B$9+Tiers!$B$12+Tiers!$B$16+C$4*Inputs!$B$5/$A9))/Tiers!$B$5 | D9: =(Tiers!$B$5-(Tiers!$B$5*Inputs!$B$8+Inputs!$B$9+Tiers!$B$12+Tiers!$B$16+D$4*Inputs!$B$5/$A9))/Tiers!$B$5 | E9: =(Tiers!$B$5-(Tiers!$B$5*Inputs!$B$8+Inputs!$B$9+Tiers!$B$12+Tiers!$B$16+E$4*Inputs!$B$5/$A9))/Tiers!$B$5 | F9: =(Tiers!$B$5-(Tiers!$B$5*Inputs!$B$8+Inputs!$B$9+Tiers!$B$12+Tiers!$B$16+F$4*Inputs!$B$5/$A9))/Tiers!$B$5
A12: Solo price needed for target margin: multiplier × pool
A14: Multiplier ↓ / Pool → | B14: =B4 | C14: =C4 | D14: =D4 | E14: =E4 | F14: =F4
A15: =A5 | B15: =(Inputs!$B$9+Tiers!$B$12+Tiers!$B$16+B$14*Inputs!$B$5/$A15)/(1-Inputs!$B$10-Inputs!$B$8) | C15: =(Inputs!$B$9+Tiers!$B$12+Tiers!$B$16+C$14*Inputs!$B$5/$A15)/(1-Inputs!$B$10-Inputs!$B$8) | D15: =(Inputs!$B$9+Tiers!$B$12+Tiers!$B$16+D$14*Inputs!$B$5/$A15)/(1-Inputs!$B$10-Inputs!$B$8) | E15: =(Inputs!$B$9+Tiers!$B$12+Tiers!$B$16+E$14*Inputs!$B$5/$A15)/(1-Inputs!$B$10-Inputs!$B$8) | F15: =(Inputs!$B$9+Tiers!$B$12+Tiers!$B$16+F$14*Inputs!$B$5/$A15)/(1-Inputs!$B$10-Inputs!$B$8)
A16: =A6 | B16: =(Inputs!$B$9+Tiers!$B$12+Tiers!$B$16+B$14*Inputs!$B$5/$A16)/(1-Inputs!$B$10-Inputs!$B$8) | C16: =(Inputs!$B$9+Tiers!$B$12+Tiers!$B$16+C$14*Inputs!$B$5/$A16)/(1-Inputs!$B$10-Inputs!$B$8) | D16: =(Inputs!$B$9+Tiers!$B$12+Tiers!$B$16+D$14*Inputs!$B$5/$A16)/(1-Inputs!$B$10-Inputs!$B$8) | E16: =(Inputs!$B$9+Tiers!$B$12+Tiers!$B$16+E$14*Inputs!$B$5/$A16)/(1-Inputs!$B$10-Inputs!$B$8) | F16: =(Inputs!$B$9+Tiers!$B$12+Tiers!$B$16+F$14*Inputs!$B$5/$A16)/(1-Inputs!$B$10-Inputs!$B$8)
A17: =A7 | B17: =(Inputs!$B$9+Tiers!$B$12+Tiers!$B$16+B$14*Inputs!$B$5/$A17)/(1-Inputs!$B$10-Inputs!$B$8) | C17: =(Inputs!$B$9+Tiers!$B$12+Tiers!$B$16+C$14*Inputs!$B$5/$A17)/(1-Inputs!$B$10-Inputs!$B$8) | D17: =(Inputs!$B$9+Tiers!$B$12+Tiers!$B$16+D$14*Inputs!$B$5/$A17)/(1-Inputs!$B$10-Inputs!$B$8) | E17: =(Inputs!$B$9+Tiers!$B$12+Tiers!$B$16+E$14*Inputs!$B$5/$A17)/(1-Inputs!$B$10-Inputs!$B$8) | F17: =(Inputs!$B$9+Tiers!$B$12+Tiers!$B$16+F$14*Inputs!$B$5/$A17)/(1-Inputs!$B$10-Inputs!$B$8)
A18: =A8 | B18: =(Inputs!$B$9+Tiers!$B$12+Tiers!$B$16+B$14*Inputs!$B$5/$A18)/(1-Inputs!$B$10-Inputs!$B$8) | C18: =(Inputs!$B$9+Tiers!$B$12+Tiers!$B$16+C$14*Inputs!$B$5/$A18)/(1-Inputs!$B$10-Inputs!$B$8) | D18: =(Inputs!$B$9+Tiers!$B$12+Tiers!$B$16+D$14*Inputs!$B$5/$A18)/(1-Inputs!$B$10-Inputs!$B$8) | E18: =(Inputs!$B$9+Tiers!$B$12+Tiers!$B$16+E$14*Inputs!$B$5/$A18)/(1-Inputs!$B$10-Inputs!$B$8) | F18: =(Inputs!$B$9+Tiers!$B$12+Tiers!$B$16+F$14*Inputs!$B$5/$A18)/(1-Inputs!$B$10-Inputs!$B$8)
A19: =A9 | B19: =(Inputs!$B$9+Tiers!$B$12+Tiers!$B$16+B$14*Inputs!$B$5/$A19)/(1-Inputs!$B$10-Inputs!$B$8) | C19: =(Inputs!$B$9+Tiers!$B$12+Tiers!$B$16+C$14*Inputs!$B$5/$A19)/(1-Inputs!$B$10-Inputs!$B$8) | D19: =(Inputs!$B$9+Tiers!$B$12+Tiers!$B$16+D$14*Inputs!$B$5/$A19)/(1-Inputs!$B$10-Inputs!$B$8) | E19: =(Inputs!$B$9+Tiers!$B$12+Tiers!$B$16+E$14*Inputs!$B$5/$A19)/(1-Inputs!$B$10-Inputs!$B$8) | F19: =(Inputs!$B$9+Tiers!$B$12+Tiers!$B$16+F$14*Inputs!$B$5/$A19)/(1-Inputs!$B$10-Inputs!$B$8)

Sheet Legend
A1: How to use this model
A2: 1. Inputs: set credit price, multiplier, Stripe, model rates, media costs, and the overhead model. Blue/yellow cells only.
A3: 2. Action Costs: tune token assumptions per action. Credits = ROUNDUP(COGS ÷ credit COGS). These rows seed the pricing_rules table in Kinika.
A4: 3. Tiers: set price, included credits, infra and overhead per tier. Read worst-case and typical margins, and the price/pool needed to hit target.
A5: 4. Typical Month: describe a realistic usage mix per tier and see pool consumption, top-up revenue and blended margin.
A6: 5. Sensitivity: Solo margin and required price across multiplier × pool. Change Solo price on Tiers and this updates.
A8: Colour code: blue text on yellow = editable input. Black = formula. Green = link from another sheet.
A9: Sources: Anthropic first-party model pricing (Sept 2026). DeepInfra Llama rate from team note. Image/video costs are estimates — replace with your provider's rates.
A10: Not modelled: social aggregator fees, support headcount, free-trial COGS, churn/LTV, annual-plan discounts.
